[
  {
    "year": -2200,
    "dynasties": [],
    "events": [
      {
        "title": "尧为部落联盟首领",
        "description": "公元前2200年前后，陶唐氏部落首领尧被推举为华夏部落联盟首领，定都于平阳（今山西临汾）。尧在位期间设置天文官观测日月星辰以制定历法，命羲和观测天象、制定历法并教导百姓按照农时耕作。尧还设立了诽谤之木让百姓批评朝政，是中国上古传说中的圣明之君。",
        "latitude": 36.08,
        "longitude": 111.5,
        "category": "政治",
        "region": "虞",
        "continent": "亚洲"
      }
    ]
  },
  {
    "year": -2190,
    "dynasties": [],
    "events": []
  },
  {
    "year": -2180,
    "dynasties": [],
    "events": []
  },
  {
    "year": -2170,
    "dynasties": [],
    "events": []
  },
  {
    "year": -2160,
    "dynasties": [],
    "events": []
  },
  {
    "year": -2150,
    "dynasties": [],
    "events": [
      {
        "title": "舜耕于历山",
        "description": "公元前2150年前后，舜在历山（今山西永济或山东济南）耕种劳作。舜虽出身微贱却以孝行闻名，他在历山耕地时得到了当地百姓的敬重，四方部落也开始听闻他的贤德之名。尧听闻舜的事迹后决定对他进行考察，为日后禅让埋下了伏笔。",
        "latitude": 36.5,
        "longitude": 112.0,
        "category": "人物",
        "region": "虞",
        "continent": "亚洲"
      }
    ]
  },
  {
    "year": -2140,
    "dynasties": [],
    "events": []
  },
  {
    "year": -2130,
    "dynasties": [],
    "events": []
  },
  {
    "year": -2120,
    "dynasties": [],
    "events": []
  },
  {
    "year": -2110,
    "dynasties": [],
    "events": []
  }
]